guard/__init__.py
guard/cli.py
guard/clients.py
guard/scanner.py
guardai-0.2.0.dist-info/LICENSE
guardai-0.2.0.dist-info/METADATA
guardai-0.2.0.dist-info/WHEEL
guardai-0.2.0.dist-info/entry_points.txt
guardai-0.2.0.dist-info/top_level.txt
guardai-0.2.0.dist-info/RECORD
