Metadata-Version: 2.1
Name: guardai
Version: 0.2.0
Summary: A CLI tool for AI-powered code security scanning
Author-email: Best Olunusi <olunusibest@gmail.com>
License: MIT
Project-URL: Homepage, https://github.com/codeguardai/guardai
Keywords: security,ai,cli,code scanning
Classifier: Programming Language :: Python :: 3
Classifier: License :: OSI Approved :: MIT License
Classifier: Operating System :: OS Independent
Requires-Python: >=3.10
License-File: LICENSE
Requires-Dist: openai>=1.40.6
Requires-Dist: PyGithub
Requires-Dist: requests
Requires-Dist: google-generativeai
Requires-Dist: ipython
Provides-Extra: dev
Requires-Dist: pylint; extra == "dev"
Requires-Dist: black; extra == "dev"
Requires-Dist: isort; extra == "dev"
